README.md
benchmarks/ViT/requirements.txt
benchmarks/ViT/run.sh
benchmarks/ViT/train.py
benchmarks/t5/README.md
benchmarks/t5/requirements.txt
benchmarks/t5/run.sh
benchmarks/t5/train.py
detonation/__init__.py
detonation/detonatiomixin.py
detonation/prepare.py
detonation/optim/DeToAdamW.py
detonation/optim/DeToSGD.py
detonation/optim/Optimizers.py
detonation/optim/__init__.py
detonation/optim/demo.py
detonation/repl/__init__.py
detonation/repl/demo_replicator.py
detonation/repl/full_replicator.py
detonation/repl/no_replicator.py
detonation/repl/random_replicator.py
detonation/repl/replicator.py
detonation/repl/slicing_replicator.py
detonation/repl/striding_replicator.py
detonation/util/__init__.py
detonation/util/dct_compress.py
detonation/util/dct_transform.py
examples/t5/README.md
examples/t5/requirements.txt
examples/t5/run.sh
examples/t5/train.py
detonation-0.5.2.dist-info/METADATA
detonation-0.5.2.dist-info/WHEEL
detonation-0.5.2.dist-info/RECORD
