Metadata-Version: 2.4
Name: detonation
Version: 0.5.2
Summary: Decouple Torch Network-Aware Training on Interlinked Online Nodes (DeToNATION)
Project-URL: Homepage, https://github.com/schneiderkamplab/DeToNATION
Project-URL: Bug Tracker, https://github.com/schneiderkamplab/DeToNATION/issues
Author: Peter Schneider-Kamp, Mogens Henrik From
Classifier: License :: OSI Approved :: MIT License
Classifier: Operating System :: OS Independent
Classifier: Programming Language :: Python :: 3
Requires-Python: >=3.11
Requires-Dist: einops
Requires-Dist: numpy
Requires-Dist: torch
Provides-Extra: all
Requires-Dist: aimrun; extra == 'all'
Requires-Dist: click; extra == 'all'
Requires-Dist: datasets; extra == 'all'
Requires-Dist: libcst; extra == 'all'
Requires-Dist: mltiming; extra == 'all'
Requires-Dist: protobuf; extra == 'all'
Requires-Dist: sentencepiece; extra == 'all'
Requires-Dist: transformers; extra == 'all'
Provides-Extra: benchmarks
Requires-Dist: aimrun; extra == 'benchmarks'
Requires-Dist: click; extra == 'benchmarks'
Requires-Dist: datasets; extra == 'benchmarks'
Requires-Dist: mltiming; extra == 'benchmarks'
Requires-Dist: protobuf; extra == 'benchmarks'
Requires-Dist: sentencepiece; extra == 'benchmarks'
Requires-Dist: transformers; extra == 'benchmarks'
Provides-Extra: dev
Requires-Dist: libcst; extra == 'dev'
Provides-Extra: examples
Requires-Dist: click; extra == 'examples'
Requires-Dist: datasets; extra == 'examples'
Requires-Dist: protobuf; extra == 'examples'
Requires-Dist: sentencepiece; extra == 'examples'
Requires-Dist: transformers; extra == 'examples'
